.bumpversion.cfg
.gitignore
MANIFEST.in
Makefile
README.rst
pypackage.mk
setup.py
docs/.gitignore
docs/Makefile
docs/epydoc.cfg
docs/gitadd.zsh
docs/sphinxtogithub.py
docs/source/api.rst.inc
docs/source/api_reference.rst
docs/source/changelog.rst
docs/source/conf.py
docs/source/credits.rst
docs/source/definitions.txt
docs/source/download.html
docs/source/fork.html
docs/source/index.rst
docs/source/my_static/.empty
docs/source/my_templates/layout.html
src/ros_node_utils/__init__.py
src/ros_node_utils.egg-info/PKG-INFO
src/ros_node_utils.egg-info/SOURCES.txt
src/ros_node_utils.egg-info/dependency_links.txt
src/ros_node_utils.egg-info/top_level.txt
src/ros_node_utils/conversions/__init__.py
src/ros_node_utils/conversions/np_images.py
src/ros_node_utils/conversions/poses.py
src/ros_node_utils/nodes/__init__.py
src/ros_node_utils/nodes/ros_logger.py
src/ros_node_utils/nodes/ros_node.py
src/ros_node_utils/nodes/wrap.py
src/ros_node_utils/tests/some_tests.py
src/rosbag_utils/__init__.py
src/rosbag_utils/rosbag_flexible_read.py
src/rosbag_utils/rosbag_info_stats.py
src/rosbag_utils/rosbag_reading.py
src/rosbag_utils/utils/__init__.py
src/rosbag_utils/utils/calling_ext_programs.py
src/rosbag_utils/utils/in_a_while.py