Metadata-Version: 1.1
Name: ros-node-utils
Version: 2.0.0
Summary: UNKNOWN
Home-page: http://github.com/AndreaCensi/ros_node_utils
Author: Andrea Censi
Author-email: censi@mit.edu
License: LGPL
Download-URL: http://github.com/AndreaCensi/ros_node_utils/tarball/2.0.0
Keywords: ROS
Platform: UNKNOWN
Classifier: Development Status :: 4 - Beta
